orz/__init__.py
orz/exceptions.py
orz/result.py
orz-0.3.3.dist-info/LICENSE
orz-0.3.3.dist-info/WHEEL
orz-0.3.3.dist-info/METADATA
orz-0.3.3.dist-info/RECORD
